falcon_mcp/__init__.py
falcon_mcp/client.py
falcon_mcp/registry.py
falcon_mcp/server.py
falcon_mcp/common/__init__.py
falcon_mcp/common/api_scopes.py
falcon_mcp/common/errors.py
falcon_mcp/common/logging.py
falcon_mcp/common/utils.py
falcon_mcp/modules/__init__.py
falcon_mcp/modules/base.py
falcon_mcp/modules/cloud.py
falcon_mcp/modules/detections.py
falcon_mcp/modules/discover.py
falcon_mcp/modules/hosts.py
falcon_mcp/modules/idp.py
falcon_mcp/modules/incidents.py
falcon_mcp/modules/intel.py
falcon_mcp/modules/sensor_usage.py
falcon_mcp/modules/serverless.py
falcon_mcp/modules/spotlight.py
falcon_mcp/resources/__init__.py
falcon_mcp/resources/cloud.py
falcon_mcp/resources/detections.py
falcon_mcp/resources/discover.py
falcon_mcp/resources/hosts.py
falcon_mcp/resources/incidents.py
falcon_mcp/resources/intel.py
falcon_mcp/resources/sensor_usage.py
falcon_mcp/resources/serverless.py
falcon_mcp/resources/spotlight.py
falcon_mcp-0.4.1.dist-info/licenses/LICENSE
falcon_mcp-0.4.1.dist-info/METADATA
falcon_mcp-0.4.1.dist-info/WHEEL
falcon_mcp-0.4.1.dist-info/entry_points.txt
falcon_mcp-0.4.1.dist-info/top_level.txt
falcon_mcp-0.4.1.dist-info/RECORD
